setup.py
factoranalysis_tk/factoranalysis.py
factoranalysis_tk.egg-info/PKG-INFO
factoranalysis_tk.egg-info/SOURCES.txt
factoranalysis_tk.egg-info/dependency_links.txt
factoranalysis_tk.egg-info/not-zip-safe
factoranalysis_tk.egg-info/top_level.txt