Metadata-Version: 1.0
Name: factoranalysis-tk
Version: 0.1
Summary: implement and test factor analysis for multivarirate data
Home-page: http://github.com/khawajts/factoranalysis_tk
Author: Taimoor Khawaja
Author-email: tmmr007@gmail.com
License: None
Platform: UNKNOWN
